alleima_tools/__init__.py
alleima_tools/alleima_tools.py
alleima_tools/cli.py
alleima_tools/cli_helpers/__init__.py
alleima_tools/cli_helpers/tests.py
alleima_tools/cli_helpers/versions.py
alleima_tools/enum.py
alleima_tools/formats/__init__.py
alleima_tools/pandas/__init__.py
alleima_tools/pandas/pydantic.py
alleima_tools/pint/__init__.py
alleima_tools/pint/math.py
alleima_tools/querylist.py
alleima_tools/utils/__init__.py
alleima_tools/utils/strings.py
alleima_tools/utils/win32.py
alleima_tools/wrappers/__init__.py
alleima_tools/wrappers/pint.py
alleima_tools-0.2.0b1.dist-info/entry_points.txt
alleima_tools-0.2.0b1.dist-info/METADATA
alleima_tools-0.2.0b1.dist-info/WHEEL
alleima_tools-0.2.0b1.dist-info/RECORD
