Metadata-Version: 2.1
Name: alleima-tools
Version: 0.2.0b1
Summary: Functions, classes, other that are useful for Alleima purposes.
Home-page: http://uskegit.app.mtrltech.com/karlwooster/AlleimaTools
Author: karlwooster
Requires-Python: >=3.9,<4.0
Classifier: Development Status :: 2 - Pre-Alpha
Classifier: Intended Audience :: Developers
Classifier: Natural Language :: English
Classifier: Programming Language :: Python :: 3
Classifier: Programming Language :: Python :: 3.9
Classifier: Programming Language :: Python :: 3.10
Classifier: Programming Language :: Python :: 3.11
Classifier: Programming Language :: Python :: 3.12
Classifier: Programming Language :: Python :: 3.6
Classifier: Programming Language :: Python :: 3.7
Classifier: Programming Language :: Python :: 3.8
Provides-Extra: cli
Provides-Extra: doc
Requires-Dist: click (>=8.1.7,<9.0.0)
Requires-Dist: marko (>=2.1.2,<3.0.0)
Requires-Dist: mkdocs (>=1.6.1,<2.0.0) ; extra == "doc"
Requires-Dist: mkdocs-autorefs (>=1.2.0,<2.0.0) ; extra == "doc"
Requires-Dist: mkdocs-include-markdown-plugin (>=6.2.2,<7.0.0) ; extra == "doc"
Requires-Dist: mkdocs-material (>=9.5.33,<10.0.0) ; extra == "doc"
Requires-Dist: mkdocs-material-extensions (>=1.3.1,<2.0.0) ; extra == "doc"
Requires-Dist: mkdocstrings[python] (>=0.25.2,<0.26.0) ; extra == "doc"
Requires-Dist: pint (>=0.23,<0.25)
Requires-Dist: pydantic (>=2.8.2,<3.0.0)
Requires-Dist: pytz (>=2024.1,<2025.0)
Requires-Dist: pywin32 (>=306,<307) ; (sys_platform == "win32") and (extra == "cli")
Requires-Dist: toml (>=0.10.2,<0.11.0)
Requires-Dist: typer (>=0.12.5,<0.13.0) ; extra == "cli"
